pioreactor_logs2slack/LEADER_ONLY
pioreactor_logs2slack/__init__.py
pioreactor_logs2slack/additional_config.ini
pioreactor_logs2slack/post_install.sh
pioreactor_logs2slack/pre_uninstall.sh
pioreactor_logs2slack-0.5.0.dist-info/LICENSE
pioreactor_logs2slack-0.5.0.dist-info/METADATA
pioreactor_logs2slack-0.5.0.dist-info/WHEEL
pioreactor_logs2slack-0.5.0.dist-info/entry_points.txt
pioreactor_logs2slack-0.5.0.dist-info/top_level.txt
pioreactor_logs2slack-0.5.0.dist-info/RECORD
