Metadata-Version: 2.1
Name: pioreactor-logs2slack
Version: 0.5.0
Summary: Push logs generated by Pioreactors to your Slack workspace
Home-page: https://github.com/Pioreactor/pioreactor-logs2slack
Author: Pioreactor
Author-email: hello@pioreactor.com
License: MIT
License-File: LICENSE
